<?xml version="1.0" encoding="utf-8"?>
<VugenScriptMetadata>
  <ScriptName>SC07_Create_And_Update_Inventory_Custom_List</ScriptName>
  <Protocol>Mobile Application - HTTP/HTML</Protocol>
  <ActionFiles>
    <FileEntry Name="vuser_init.c" Filter="2" />
    <FileEntry Name="Action.c" Filter="2" />
    <FileEntry Name="vuser_end.c" Filter="2" />
  </ActionFiles>
  <GeneralFiles>
    <FileEntry Name="SC07_Create_And_Update_Inventory_Custom_List.usr" Filter="4" />
    <FileEntry Name="default.cfg" Filter="4" />
    <FileEntry Name="default.usp" Filter="4" />
    <FileEntry Name="SC07_Create_And_Update_Inventory_Custom_List.prm" Filter="2" />
    <FileEntry Name="globals.h" Filter="2" />
    <FileEntry Name="P_Password.dat" Filter="2" />
    <FileEntry Name="P_URL.dat" Filter="2" />
    <FileEntry Name="P_UserID.dat" Filter="2" />
    <FileEntry Name="P_CustomerID.dat" Filter="2" />
    <FileEntry Name="P_OpCo.dat" Filter="2" />
    <FileEntry Name="P_WSURL.dat" Filter="2" />
    <FileEntry Name="ScriptUploadMetadata.xml" Filter="2" />
    <FileEntry Name="Bookmarks.xml" Filter="2" />
    <FileEntry Name="Breakpoints.xml" Filter="2" />
    <FileEntry Name="CompilerLogMetadata.xml" Filter="2" />
    <FileEntry Name="ReplaySummaryReport.xml" Filter="2" />
    <FileEntry Name="UserTasks.xml" Filter="2" />
    <FileEntry Name="combined_SC07_Create_And_Update_Inventory_Custom_List.c" Filter="2" />
    <FileEntry Name="pre_cci.c" Filter="2" />
    <FileEntry Name="11656991344.idx" Filter="1" />
    <FileEntry Name="19904798844.idx" Filter="1" />
    <FileEntry Name="21154114144.idx" Filter="1" />
    <FileEntry Name="21154114144_2p1.891.idx" Filter="1" />
    <FileEntry Name="21154114144_eKr.323.idx" Filter="1" />
    <FileEntry Name="21154114144_keu.395.idx" Filter="1" />
    <FileEntry Name="21154114144_Ml4.727.idx" Filter="1" />
    <FileEntry Name="21154114144_Ort.545.idx" Filter="1" />
    <FileEntry Name="21154114144_p4z.439.idx" Filter="1" />
    <FileEntry Name="21154114144_R5v.77.idx" Filter="1" />
    <FileEntry Name="21154114144_XFA.669.idx" Filter="1" />
    <FileEntry Name="21931459044.idx" Filter="1" />
    <FileEntry Name="25010820744.idx" Filter="1" />
    <FileEntry Name="25010820744_094.546.idx" Filter="1" />
    <FileEntry Name="25010820744_11M.892.idx" Filter="1" />
    <FileEntry Name="25010820744_hU4.440.idx" Filter="1" />
    <FileEntry Name="25010820744_jd7.78.idx" Filter="1" />
    <FileEntry Name="25010820744_mp4.670.idx" Filter="1" />
    <FileEntry Name="25010820744_qXw.324.idx" Filter="1" />
    <FileEntry Name="25010820744_VIh.396.idx" Filter="1" />
    <FileEntry Name="25010820744_Z5N.728.idx" Filter="1" />
    <FileEntry Name="25280300444.idx" Filter="1" />
    <FileEntry Name="25303465144.idx" Filter="1" />
    <FileEntry Name="39928544.idx" Filter="1" />
    <FileEntry Name="6288947044.idx" Filter="1" />
    <FileEntry Name="6565917744.idx" Filter="1" />
    <FileEntry Name="7638924144.idx" Filter="1" />
    <FileEntry Name="9072179644.idx" Filter="1" />
    <FileEntry Name="Create_and_Update_Inventory_New_0530_URLmode.prm.bak" Filter="1" />
    <FileEntry Name="logfile.log" Filter="1" />
    <FileEntry Name="mdrv.log" Filter="1" />
    <FileEntry Name="mdrv_cmd.txt" Filter="1" />
    <FileEntry Name="options.txt" Filter="1" />
    <FileEntry Name="output.bak" Filter="1" />
    <FileEntry Name="output.txt" Filter="1" />
    <FileEntry Name="P_Quantity.dat" Filter="1" />
    <FileEntry Name="replay.har" Filter="1" />
    <FileEntry Name="SC07_Create_And_Update_Inventory_Custom_List.c.pickle" Filter="1" />
    <FileEntry Name="SC07_Create_And_Update_Inventory_Custom_List.ci" Filter="1" />
    <FileEntry Name="SC07_Create_And_Update_Inventory_Custom_List.prm.bak" Filter="1" />
    <FileEntry Name="SC07_Create_And_Update_Inventory_Custom_List.sdf" Filter="1" />
    <FileEntry Name="shunra.shunra" Filter="1" />
    <FileEntry Name="ssr_config.ini" Filter="1" />
    <FileEntry Name="ThumbnailsCache.tmp" Filter="1" />
    <FileEntry Name="TransactionsData.db" Filter="1" />
    <FileEntry Name="data\" Filter="1" />
    <FileEntry Name="result1\" Filter="1" />
    <FileEntry Name="result2\" Filter="1" />
    <FileEntry Name="result3\" Filter="1" />
  </GeneralFiles>
</VugenScriptMetadata>